num2fawords/__init__.py
num2fawords/__main__.py
num2fawords/test.py
num2fawords-1.1.dist-info/DESCRIPTION.rst
num2fawords-1.1.dist-info/METADATA
num2fawords-1.1.dist-info/RECORD
num2fawords-1.1.dist-info/WHEEL
num2fawords-1.1.dist-info/metadata.json
num2fawords-1.1.dist-info/top_level.txt
