Metadata-Version: 1.1
Name: num2fawords
Version: 1.1
Summary: A tool to convert numbers (int, float) into Persian words
Home-page: https://github.com/5j9/num2fawords
Author: 5j9
Author-email: 5j9@users.noreply.github.com
License: GNU General Public License v3.0
Keywords: convert number words farsi persian
Platform: UNKNOWN
Classifier: Development Status :: 5 - Production/Stable
Classifier: Intended Audience :: Developers
Classifier: Intended Audience :: End Users/Desktop
Classifier: License :: OSI Approved :: GNU General Public License v3 or later (GPLv3+)
Classifier: Natural Language :: English
Classifier: Natural Language :: Persian
Classifier: Programming Language :: Python :: 3.3
Classifier: Programming Language :: Python :: 3.4
Classifier: Programming Language :: Python :: 3.5
Classifier: Programming Language :: Python :: 3.6
Classifier: Topic :: Text Processing :: General
